capellambse_context_diagrams/__init__.py
capellambse_context_diagrams/_elkjs.py
capellambse_context_diagrams/_registry.py
capellambse_context_diagrams/context.py
capellambse_context_diagrams/custom_diagram.py
capellambse_context_diagrams/enums.py
capellambse_context_diagrams/errors.py
capellambse_context_diagrams/filters.py
capellambse_context_diagrams/helpers.py
capellambse_context_diagrams/py.typed
capellambse_context_diagrams/serializers.py
capellambse_context_diagrams/styling.py
capellambse_context_diagrams/builders/__init__.py
capellambse_context_diagrams/builders/_makers.py
capellambse_context_diagrams/builders/dataflow.py
capellambse_context_diagrams/builders/default.py
capellambse_context_diagrams/builders/derived.py
capellambse_context_diagrams/builders/diagram_view.py
capellambse_context_diagrams/builders/fchain.py
capellambse_context_diagrams/builders/interface.py
capellambse_context_diagrams/collectors/__init__.py
capellambse_context_diagrams/collectors/_generic.py
capellambse_context_diagrams/collectors/cable_tree.py
capellambse_context_diagrams/collectors/dataflow_view.py
capellambse_context_diagrams/collectors/default.py
capellambse_context_diagrams/collectors/diagram_view.py
capellambse_context_diagrams/collectors/exchanges.py
capellambse_context_diagrams/collectors/portless.py
capellambse_context_diagrams/collectors/realization_view.py
capellambse_context_diagrams/collectors/tree_view.py
capellambse_context_diagrams/interop/deno.json
capellambse_context_diagrams/interop/deno.json.license
capellambse_context_diagrams/interop/elk.ts
capellambse_context_diagrams/interop/elkgraph-json.ts
capellambse_context_diagrams/interop/elkgraph-to-sprotty.ts
capellambse_context_diagrams-0.8.1.dist-info/METADATA
capellambse_context_diagrams-0.8.1.dist-info/WHEEL
capellambse_context_diagrams-0.8.1.dist-info/entry_points.txt
capellambse_context_diagrams-0.8.1.dist-info/top_level.txt
capellambse_context_diagrams-0.8.1.dist-info/RECORD
