Metadata-Version: 2.4
Name: capellambse-context-diagrams
Version: 0.8.1
Summary: Extension for py-capellambse that adds automatically generated context diagrams for arbitrary model elements.
Author: DB InfraGO AG
License: Apache-2.0
Project-URL: Homepage, https://github.com/dbinfrago/capellambse-context-diagrams
Project-URL: Documentation, https://capellambse-context-diagrams.readthedocs.io
Keywords: capella,mbse,context,diagram,automatic diagrams
Platform: any
Classifier: Development Status :: 5 - Production/Stable
Classifier: Intended Audience :: Developers
Classifier: License :: OSI Approved :: Apache Software License
Classifier: Natural Language :: English
Classifier: Operating System :: OS Independent
Classifier: Programming Language :: Python :: 3 :: Only
Classifier: Programming Language :: Python :: 3.11
Classifier: Programming Language :: Python :: 3.12
Classifier: Programming Language :: Python :: 3.13
Classifier: Topic :: Other/Nonlisted Topic
Classifier: Topic :: Scientific/Engineering
Classifier: Topic :: Software Development :: Libraries :: Python Modules
Classifier: Typing :: Typed
Requires-Python: <3.15,>=3.11
Requires-Dist: capellambse<0.9,>=0.8.0
Requires-Dist: platformdirs>=4.3.7
Requires-Dist: typing_extensions>=4.15.0
Requires-Dist: pydantic>=2.8.0
